numpy_image_widget/__init__.py
numpy_image_widget/monotext_widget.py
numpy_image_widget/numpy_image_widget.py
numpy_image_widget-2020.7.21.dist-info/LICENSE
numpy_image_widget-2020.7.21.dist-info/METADATA
numpy_image_widget-2020.7.21.dist-info/WHEEL
numpy_image_widget-2020.7.21.dist-info/top_level.txt
numpy_image_widget-2020.7.21.dist-info/RECORD
