Metadata-Version: 2.1
Name: numpy-image-widget
Version: 2020.7.21
Summary: An easy-to-use Jupyter widget for displaying images from Numpy data arrays
Home-page: https://github.com/who8mylunch/Numpy_Image_Widget
Author: Pierre V. Villeneuve
Author-email: pierre.villeneuve@gmail.com
License: MIT
Keywords: jupyter,widget,numpy,image
Platform: UNKNOWN
Requires-Dist: numpy
Requires-Dist: image-attendant
Requires-Dist: ipyevents
Requires-Dist: ipywidgets
